oauth2client/__init__.py
oauth2client/_helpers.py
oauth2client/_openssl_crypt.py
oauth2client/_pkce.py
oauth2client/_pure_python_crypt.py
oauth2client/_pycrypto_crypt.py
oauth2client/client.py
oauth2client/clientsecrets.py
oauth2client/crypt.py
oauth2client/file.py
oauth2client/service_account.py
oauth2client/tools.py
oauth2client/transport.py
oauth2client/contrib/__init__.py
oauth2client/contrib/_appengine_ndb.py
oauth2client/contrib/_metadata.py
oauth2client/contrib/appengine.py
oauth2client/contrib/devshell.py
oauth2client/contrib/dictionary_storage.py
oauth2client/contrib/flask_util.py
oauth2client/contrib/gce.py
oauth2client/contrib/keyring_storage.py
oauth2client/contrib/multiprocess_file_storage.py
oauth2client/contrib/sqlalchemy.py
oauth2client/contrib/xsrfutil.py
oauth2client/contrib/django_util/__init__.py
oauth2client/contrib/django_util/apps.py
oauth2client/contrib/django_util/decorators.py
oauth2client/contrib/django_util/models.py
oauth2client/contrib/django_util/signals.py
oauth2client/contrib/django_util/site.py
oauth2client/contrib/django_util/storage.py
oauth2client/contrib/django_util/views.py
tests/__init__.py
tests/conftest.py
tests/http_mock.py
tests/test__helpers.py
tests/test__pkce.py
tests/test__pure_python_crypt.py
tests/test__pycrypto_crypt.py
tests/test_client.py
tests/test_clientsecrets.py
tests/test_crypt.py
tests/test_file.py
tests/test_jwt.py
tests/test_service_account.py
tests/test_tools.py
tests/test_transport.py
tests/contrib/__init__.py
tests/contrib/test_devshell.py
tests/contrib/test_dictionary_storage.py
tests/contrib/test_flask_util.py
tests/contrib/test_gce.py
tests/contrib/test_keyring_storage.py
tests/contrib/test_metadata.py
tests/contrib/test_multiprocess_file_storage.py
tests/contrib/test_sqlalchemy.py
tests/contrib/test_xsrfutil.py
tests/contrib/appengine/__init__.py
tests/contrib/appengine/conftest.py
tests/contrib/appengine/test__appengine_ndb.py
oauth2client-4.1.1.dist-info/top_level.txt
oauth2client-4.1.1.dist-info/METADATA
oauth2client-4.1.1.dist-info/DESCRIPTION.rst
oauth2client-4.1.1.dist-info/metadata.json
oauth2client-4.1.1.dist-info/WHEEL
oauth2client-4.1.1.dist-info/RECORD
